<annotation>
    <folder>images</folder>
    <filename>maksssksksss504.png</filename>
    <path>/Users/kimhyunwoo/Desktop/Programming /Personal/Git/WAAT/Python_/images/maksssksksss504.png</path>
    <source>
        <database>Unknown</database>
    </source>
    <size>
        <width>301</width>
        <height>400</height>
        <depth>3</depth>
    </size>
    <segmented>0</segmented>
    <object>
        <name>1</name>
        <pose>Unspecified</pose>
        <truncated>0</truncated>
        <difficult>0</difficult>
        <bndbox>
            <xmin>0.6203777194023132</xmin>
            <ymin>116.50379943847656</ymin>
            <xmax>290.1239318847656</xmax>
            <ymax>369.02838134765625</ymax>
        </bndbox>
    </object>
</annotation>
