<annotation>
    <folder>images</folder>
    <filename>maksssksksss7.png</filename>
    <path>/Users/kimhyunwoo/Desktop/Programming /Personal/Git/WAAT/Python_/images/maksssksksss7.png</path>
    <source>
        <database>Unknown</database>
    </source>
    <size>
        <width>400</width>
        <height>300</height>
        <depth>3</depth>
    </size>
    <segmented>0</segmented>
    <object>
        <name>1</name>
        <pose>Unspecified</pose>
        <truncated>0</truncated>
        <difficult>0</difficult>
        <bndbox>
            <xmin>217.21273803710938</xmin>
            <ymin>68.295654296875</ymin>
            <xmax>390.09136962890625</xmax>
            <ymax>296.5138244628906</ymax>
        </bndbox>
    </object>    <object>
        <name>1</name>
        <pose>Unspecified</pose>
        <truncated>0</truncated>
        <difficult>0</difficult>
        <bndbox>
            <xmin>35.927101135253906</xmin>
            <ymin>54.17277145385742</ymin>
            <xmax>138.02212524414062</xmax>
            <ymax>177.37132263183594</ymax>
        </bndbox>
    </object>    <object>
        <name>1</name>
        <pose>Unspecified</pose>
        <truncated>0</truncated>
        <difficult>0</difficult>
        <bndbox>
            <xmin>26.429931640625</xmin>
            <ymin>104.5450210571289</ymin>
            <xmax>233.29415893554688</xmax>
            <ymax>295.7937316894531</ymax>
        </bndbox>
    </object>    <object>
        <name>1</name>
        <pose>Unspecified</pose>
        <truncated>0</truncated>
        <difficult>0</difficult>
        <bndbox>
            <xmin>114.27657318115234</xmin>
            <ymin>56.49992370605469</ymin>
            <xmax>149.3347625732422</xmax>
            <ymax>119.94111633300781</ymax>
        </bndbox>
    </object>    <object>
        <name>1</name>
        <pose>Unspecified</pose>
        <truncated>0</truncated>
        <difficult>0</difficult>
        <bndbox>
            <xmin>129.0810546875</xmin>
            <ymin>64.39257049560547</ymin>
            <xmax>287.369384765625</xmax>
            <ymax>282.1288757324219</ymax>
        </bndbox>
    </object>
</annotation>
