<annotation>
    <folder>images</folder>
    <filename>maksssksksss180.png</filename>
    <path>/Users/kimhyunwoo/Desktop/Programming /Personal/Git/WAAT/Python_/images/maksssksksss180.png</path>
    <source>
        <database>Unknown</database>
    </source>
    <size>
        <width>301</width>
        <height>400</height>
        <depth>3</depth>
    </size>
    <segmented>0</segmented>
    <object>
        <name>1</name>
        <pose>Unspecified</pose>
        <truncated>0</truncated>
        <difficult>0</difficult>
        <bndbox>
            <xmin>0.0</xmin>
            <ymin>146.32192993164062</ymin>
            <xmax>299.77191162109375</xmax>
            <ymax>400.0</ymax>
        </bndbox>
    </object>
</annotation>
