<annotation>
    <folder>images</folder>
    <filename>maksssksksss771.png</filename>
    <path>/Users/kimhyunwoo/Desktop/Programming /Personal/Git/WAAT/Python_/images/maksssksksss771.png</path>
    <source>
        <database>Unknown</database>
    </source>
    <size>
        <width>400</width>
        <height>267</height>
        <depth>3</depth>
    </size>
    <segmented>0</segmented>
    <object>
        <name>1</name>
        <pose>Unspecified</pose>
        <truncated>0</truncated>
        <difficult>0</difficult>
        <bndbox>
            <xmin>11.525065422058105</xmin>
            <ymin>35.22026824951172</ymin>
            <xmax>163.39114379882812</xmax>
            <ymax>267.0</ymax>
        </bndbox>
    </object>    <object>
        <name>1</name>
        <pose>Unspecified</pose>
        <truncated>0</truncated>
        <difficult>0</difficult>
        <bndbox>
            <xmin>196.9308319091797</xmin>
            <ymin>15.78553581237793</ymin>
            <xmax>400.0</xmax>
            <ymax>263.8639221191406</ymax>
        </bndbox>
    </object>    <object>
        <name>1</name>
        <pose>Unspecified</pose>
        <truncated>0</truncated>
        <difficult>0</difficult>
        <bndbox>
            <xmin>93.96232604980469</xmin>
            <ymin>27.021512985229492</ymin>
            <xmax>289.98095703125</xmax>
            <ymax>266.0856018066406</ymax>
        </bndbox>
    </object>
</annotation>
