<annotation>
    <folder>images</folder>
    <filename>maksssksksss679.png</filename>
    <path>/Users/kimhyunwoo/Desktop/Programming /Personal/Git/WAAT/Python_/images/maksssksksss679.png</path>
    <source>
        <database>Unknown</database>
    </source>
    <size>
        <width>400</width>
        <height>225</height>
        <depth>3</depth>
    </size>
    <segmented>0</segmented>
    <object>
        <name>1</name>
        <pose>Unspecified</pose>
        <truncated>0</truncated>
        <difficult>0</difficult>
        <bndbox>
            <xmin>226.459228515625</xmin>
            <ymin>18.240886688232422</ymin>
            <xmax>400.0</xmax>
            <ymax>220.8516082763672</ymax>
        </bndbox>
    </object>    <object>
        <name>1</name>
        <pose>Unspecified</pose>
        <truncated>0</truncated>
        <difficult>0</difficult>
        <bndbox>
            <xmin>11.000417709350586</xmin>
            <ymin>15.751018524169922</ymin>
            <xmax>236.9362030029297</xmax>
            <ymax>224.26011657714844</ymax>
        </bndbox>
    </object>
</annotation>
