<annotation>
    <folder>images</folder>
    <filename>maksssksksss185.png</filename>
    <path>/Users/kimhyunwoo/Desktop/Programming /Personal/Git/WAAT/Python_/images/maksssksksss185.png</path>
    <source>
        <database>Unknown</database>
    </source>
    <size>
        <width>400</width>
        <height>267</height>
        <depth>3</depth>
    </size>
    <segmented>0</segmented>
    <object>
        <name>1</name>
        <pose>Unspecified</pose>
        <truncated>0</truncated>
        <difficult>0</difficult>
        <bndbox>
            <xmin>24.745647430419922</xmin>
            <ymin>97.56632995605469</ymin>
            <xmax>236.13653564453125</xmax>
            <ymax>267.0</ymax>
        </bndbox>
    </object>    <object>
        <name>1</name>
        <pose>Unspecified</pose>
        <truncated>0</truncated>
        <difficult>0</difficult>
        <bndbox>
            <xmin>238.29031372070312</xmin>
            <ymin>49.65084457397461</ymin>
            <xmax>301.85479736328125</xmax>
            <ymax>202.6143798828125</ymax>
        </bndbox>
    </object>    <object>
        <name>1</name>
        <pose>Unspecified</pose>
        <truncated>0</truncated>
        <difficult>0</difficult>
        <bndbox>
            <xmin>197.12864685058594</xmin>
            <ymin>39.16700744628906</ymin>
            <xmax>272.5660705566406</xmax>
            <ymax>216.7122039794922</ymax>
        </bndbox>
    </object>    <object>
        <name>1</name>
        <pose>Unspecified</pose>
        <truncated>0</truncated>
        <difficult>0</difficult>
        <bndbox>
            <xmin>149.49264526367188</xmin>
            <ymin>53.737789154052734</ymin>
            <xmax>262.8717956542969</xmax>
            <ymax>241.89346313476562</ymax>
        </bndbox>
    </object>
</annotation>
