<annotation>
    <folder>images</folder>
    <filename>maksssksksss811.png</filename>
    <path>/Users/kimhyunwoo/Desktop/Programming /Personal/Git/WAAT/Python_/images/maksssksksss811.png</path>
    <source>
        <database>Unknown</database>
    </source>
    <size>
        <width>267</width>
        <height>400</height>
        <depth>3</depth>
    </size>
    <segmented>0</segmented>
    <object>
        <name>1</name>
        <pose>Unspecified</pose>
        <truncated>0</truncated>
        <difficult>0</difficult>
        <bndbox>
            <xmin>2.6678407192230225</xmin>
            <ymin>2.2961020469665527</ymin>
            <xmax>267.0</xmax>
            <ymax>399.2042236328125</ymax>
        </bndbox>
    </object>
</annotation>
