<annotation>
    <folder>images</folder>
    <filename>maksssksksss655.png</filename>
    <path>/Users/kimhyunwoo/Desktop/Programming /Personal/Git/WAAT/Python_/images/maksssksksss655.png</path>
    <source>
        <database>Unknown</database>
    </source>
    <size>
        <width>301</width>
        <height>400</height>
        <depth>3</depth>
    </size>
    <segmented>0</segmented>
    <object>
        <name>1</name>
        <pose>Unspecified</pose>
        <truncated>0</truncated>
        <difficult>0</difficult>
        <bndbox>
            <xmin>1.0436896085739136</xmin>
            <ymin>124.50296020507812</ymin>
            <xmax>296.3935546875</xmax>
            <ymax>398.99078369140625</ymax>
        </bndbox>
    </object>
</annotation>
